{
  "project_info": {
    "project_number": "513409026745",
    "project_id": "moviemaniac-f07bb",
    "storage_bucket": "moviemaniac-f07bb.appspot.com"
  },
  "client": [
    {
      "client_info": {
        "mobilesdk_app_id": "1:513409026745:android:b546e4f1ceed09a4cf2968",
        "android_client_info": {
          "package_name": "com.example.moviemaniac"
        }
      },
      "oauth_client": [
        {
          "client_id": "513409026745-j4iqqu8usthdm7hmoqankd3uh1j3k5m1.apps.googleusercontent.com",
          "client_type": 3
        }
      ],
      "api_key": [
        {
          "current_key": "AIzaSyDWgRmeydHtGImD29_-QL9P177b-aEmuxE"
        }
      ],
      "services": {
        "appinvite_service": {
          "other_platform_oauth_client": [
            {
              "client_id": "513409026745-j4iqqu8usthdm7hmoqankd3uh1j3k5m1.apps.googleusercontent.com",
              "client_type": 3
            }
          ]
        }
      }
    }
  ],
  "configuration_version": "1"
}